dbridge/__about__.py
dbridge/__init__.py
dbridge/config.py
dbridge/adapters/__init__.py
dbridge/adapters/capabilities.py
dbridge/adapters/interfaces.py
dbridge/adapters/dbs/__init__.py
dbridge/adapters/dbs/duckdb.py
dbridge/adapters/dbs/models.py
dbridge/adapters/dbs/mysql.py
dbridge/adapters/dbs/postgres.py
dbridge/adapters/dbs/snowflake.py
dbridge/adapters/dbs/sqllite.py
dbridge/exceptions/__init__.py
dbridge/logging/__init__.py
dbridge/output_formatters/__init__.py
dbridge/scripts/extract_table.py
dbridge/server/__init__.py
dbridge/server/app.py
dbridge/server/caching.py
dbridge/server/config.py
dbridge-0.2.10.dist-info/METADATA
dbridge-0.2.10.dist-info/WHEEL
dbridge-0.2.10.dist-info/licenses/LICENSE.txt
dbridge-0.2.10.dist-info/RECORD
